click_use_empty_env/__init__.py
click_use_empty_env/patch.py
click_use_empty_env-1.0.0.dist-info/WHEEL
click_use_empty_env-1.0.0.dist-info/METADATA
click_use_empty_env-1.0.0.dist-info/RECORD
