Metadata-Version: 2.1
Name: click-use-empty-env
Version: 1.0.0
Summary: A very small addon package to click that restores the ability to use empty values from env variables.
Home-page: https://github.com/ulope/click-use-emty-env
License: MIT
Author: Ulrich Petri
Author-email: python@ulo.pe
Requires-Python: >=3.7
Classifier: License :: OSI Approved :: MIT License
Classifier: Programming Language :: Python :: 3
Classifier: Programming Language :: Python :: 3.10
Classifier: Programming Language :: Python :: 3.7
Classifier: Programming Language :: Python :: 3.8
Classifier: Programming Language :: Python :: 3.9
Requires-Dist: click (>=7.1.0)
Project-URL: Repository, https://github.com/ulope/click-use-emty-env
